{
  "avg": {
    "14": [
      "145.0"
    ], 
    "48": [
      "1020.0"
    ], 
    "59": [
      "135.8"
    ], 
    "76": [
      "504.0", 
      "531.0"
    ], 
    "79": [
      "508.0"
    ], 
    "80": [
      "560.0", 
      "545.0", 
      "505.0"
    ], 
    "81": [
      "561.0", 
      "506.0"
    ], 
    "82": [
      "541.0", 
      "507.0"
    ], 
    "84": [
      "503.0"
    ], 
    "86": [
      "510.0"
    ], 
    "90": [
      "509.0"
    ], 
    "104": [
      "102.0"
    ], 
    "124": [
      "1010.0"
    ], 
    "128": [
      "101.0"
    ], 
    "137": [
      "534.0"
    ], 
    "139": [
      "528.0"
    ], 
    "145": [
      "516.0"
    ], 
    "149": [
      "124.6"
    ], 
    "150": [
      "124.2"
    ], 
    "152": [
      "525.0"
    ], 
    "154": [
      "124.4", 
      "124.5", 
      "519.0"
    ], 
    "158": [
      "123.3"
    ], 
    "159": [
      "123.2", 
      "123.1"
    ], 
    "160": [
      "124.1"
    ], 
    "163": [
      "521.0"
    ], 
    "170": [
      "551.0"
    ], 
    "171": [
      "140.52"
    ], 
    "174": [
      "523.0"
    ], 
    "182": [
      "105.0"
    ], 
    "189": [
      "513.0"
    ], 
    "190": [
      "562.0"
    ], 
    "201": [
      "5.2"
    ], 
    "205": [
      "555.0"
    ], 
    "206": [
      "5.3"
    ], 
    "207": [
      "250399.0"
    ], 
    "215": [
      "5.4"
    ], 
    "224": [
      "5.1"
    ], 
    "225": [
      "136.7611"
    ], 
    "227": [
      "136.733"
    ], 
    "232": [
      "135.13"
    ], 
    "233": [
      "5.5", 
      "5.7"
    ], 
    "234": [
      "134.813", 
      "5.6"
    ], 
    "235": [
      "1030.0"
    ], 
    "249": [
      "500199.0"
    ], 
    "253": [
      "1325.5"
    ], 
    "260": [
      "1308.0"
    ], 
    "263": [
      "1325.3"
    ], 
    "266": [
      "4008.0"
    ], 
    "267": [
      "103.0"
    ], 
    "273": [
      "1307.0"
    ], 
    "277": [
      "1.0"
    ], 
    "278": [
      "106.0"
    ], 
    "282": [
      "8.0"
    ], 
    "286": [
      "140.51"
    ], 
    "292": [
      "514.0", 
      "1325.1"
    ], 
    "298": [
      "140.54"
    ], 
    "301": [
      "150.3"
    ], 
    "306": [
      "110.0", 
      "129.0"
    ], 
    "308": [
      "128.0"
    ], 
    "309": [
      "150.2"
    ], 
    "312": [
      "120.0", 
      "140.53"
    ], 
    "316": [
      "127.0"
    ], 
    "317": [
      "135.2"
    ], 
    "323": [
      "122.0", 
      "150.1"
    ], 
    "325": [
      "126.0"
    ], 
    "328": [
      "2.0"
    ], 
    "330": [
      "135.3"
    ], 
    "334": [
      "7.0"
    ], 
    "337": [
      "135.4"
    ], 
    "339": [
      "4002.0"
    ], 
    "341": [
      "144.6"
    ], 
    "344": [
      "535.0"
    ], 
    "351": [
      "4003.0", 
      "135.11"
    ], 
    "355": [
      "135.6"
    ], 
    "356": [
      "7.1"
    ], 
    "358": [
      "135.1"
    ], 
    "359": [
      "556.0"
    ], 
    "363": [
      "130.0", 
      "135.9"
    ], 
    "370": [
      "4.22"
    ], 
    "371": [
      "4001.0"
    ], 
    "372": [
      "111.0"
    ], 
    "375": [
      "131.0"
    ], 
    "379": [
      "135.5"
    ], 
    "384": [
      "125.0"
    ], 
    "385": [
      "1301.0"
    ], 
    "387": [
      "119.0"
    ], 
    "391": [
      "17.0"
    ], 
    "392": [
      "18.0"
    ], 
    "393": [
      "250403.0"
    ], 
    "398": [
      "250407.0"
    ], 
    "399": [
      "135.7"
    ], 
    "400": [
      "13.0"
    ], 
    "401": [
      "15.0"
    ], 
    "403": [
      "250406.0"
    ], 
    "404": [
      "135.12"
    ], 
    "408": [
      "250400.0"
    ], 
    "415": [
      "6.0"
    ], 
    "417": [
      "1003.0"
    ], 
    "426": [
      "113.0", 
      "250408.0"
    ], 
    "428": [
      "19.0"
    ], 
    "429": [
      "4007.0"
    ], 
    "431": [
      "112.0"
    ], 
    "435": [
      "121.0"
    ], 
    "437": [
      "21.0"
    ], 
    "441": [
      "115.0"
    ], 
    "443": [
      "250405.0"
    ], 
    "444": [
      "20.0"
    ], 
    "446": [
      "250409.0"
    ], 
    "447": [
      "250402.0", 
      "10024.5"
    ], 
    "449": [
      "1002.0"
    ], 
    "453": [
      "132.0"
    ], 
    "456": [
      "16.0"
    ], 
    "458": [
      "117.0"
    ], 
    "463": [
      "10024.3"
    ], 
    "464": [
      "114.0", 
      "107.0"
    ], 
    "465": [
      "116.0", 
      "134.0"
    ], 
    "468": [
      "25406.0", 
      "4.6"
    ], 
    "473": [
      "1302.0"
    ], 
    "482": [
      "4000.0", 
      "552.0"
    ], 
    "483": [
      "12.0"
    ], 
    "491": [
      "10024.1"
    ], 
    "499": [
      "3.0"
    ], 
    "501": [
      "108.0"
    ], 
    "509": [
      "133.0"
    ], 
    "511": [
      "22.0"
    ], 
    "520": [
      "302.0", 
      "27.0"
    ], 
    "530": [
      "26.0"
    ], 
    "546": [
      "32.0"
    ], 
    "550": [
      "1321.0"
    ], 
    "559": [
      "524.0"
    ], 
    "562": [
      "250199.0"
    ], 
    "563": [
      "1349.0"
    ], 
    "568": [
      "300.0", 
      "134.99602"
    ], 
    "569": [
      "43.0"
    ], 
    "570": [
      "30.0"
    ], 
    "571": [
      "34.0"
    ], 
    "573": [
      "517.0"
    ], 
    "576": [
      "500200.1", 
      "4.24"
    ], 
    "577": [
      "134.805"
    ], 
    "578": [
      "530.0"
    ], 
    "581": [
      "9.0"
    ], 
    "585": [
      "4.25"
    ], 
    "586": [
      "1350.0", 
      "527.0", 
      "1355.0"
    ], 
    "588": [
      "4.64", 
      "4.43"
    ], 
    "591": [
      "134.702"
    ], 
    "592": [
      "118.0"
    ], 
    "595": [
      "134.911", 
      "4.62"
    ], 
    "596": [
      "45.0", 
      "4.42"
    ], 
    "597": [
      "1366.0", 
      "134.708"
    ], 
    "599": [
      "200.0"
    ], 
    "600": [
      "1315.0", 
      "1364.0", 
      "134.706"
    ], 
    "602": [
      "109.0"
    ], 
    "603": [
      "1330.0"
    ], 
    "605": [
      "23.0"
    ], 
    "606": [
      "134.811"
    ], 
    "607": [
      "38.0"
    ], 
    "609": [
      "39.0"
    ], 
    "611": [
      "134.71"
    ], 
    "612": [
      "4.61", 
      "1353.0"
    ], 
    "614": [
      "4.54"
    ], 
    "616": [
      "1309.0", 
      "134.802"
    ], 
    "617": [
      "4.74"
    ], 
    "618": [
      "4.71", 
      "29.0"
    ], 
    "622": [
      "139901.0"
    ], 
    "623": [
      "24.0", 
      "1354.0"
    ], 
    "626": [
      "33.0"
    ], 
    "627": [
      "1365.0", 
      "134.902"
    ], 
    "629": [
      "44.0", 
      "1317.0"
    ], 
    "630": [
      "4.23"
    ], 
    "631": [
      "134.904", 
      "4.68"
    ], 
    "632": [
      "205.0"
    ], 
    "633": [
      "1327.0"
    ], 
    "634": [
      "134.99601", 
      "1352.0"
    ], 
    "635": [
      "4.75"
    ], 
    "636": [
      "4.67", 
      "1310.0", 
      "134.812"
    ], 
    "639": [
      "134.809", 
      "4.4"
    ], 
    "641": [
      "4.76"
    ], 
    "643": [
      "134.906"
    ], 
    "644": [
      "35.0", 
      "4.63"
    ], 
    "647": [
      "1344.0"
    ], 
    "648": [
      "1340.0"
    ], 
    "649": [
      "37.0", 
      "134.804"
    ], 
    "650": [
      "1319.0"
    ], 
    "651": [
      "134.701"
    ], 
    "652": [
      "1348.0", 
      "139902.0"
    ], 
    "653": [
      "4.44", 
      "10.0", 
      "1347.0"
    ], 
    "657": [
      "4.36"
    ], 
    "658": [
      "1318.0", 
      "1336.0"
    ], 
    "659": [
      "134.99603", 
      "1313.0"
    ], 
    "660": [
      "134.909", 
      "1335.0", 
      "134.801"
    ], 
    "663": [
      "1314.0"
    ], 
    "665": [
      "134.912", 
      "11.0"
    ], 
    "667": [
      "136.778"
    ], 
    "669": [
      "4.45", 
      "4.27"
    ], 
    "672": [
      "4.53"
    ], 
    "674": [
      "1322.0"
    ], 
    "676": [
      "1316.0"
    ], 
    "677": [
      "36.0", 
      "554.0"
    ], 
    "679": [
      "301.0"
    ], 
    "680": [
      "134.91"
    ], 
    "681": [
      "4.57"
    ], 
    "683": [
      "134.803"
    ], 
    "685": [
      "134.905"
    ], 
    "687": [
      "1337.0"
    ], 
    "688": [
      "520.0", 
      "1338.0", 
      "1333.0"
    ], 
    "689": [
      "1331.0"
    ], 
    "694": [
      "1324.0", 
      "134.903"
    ], 
    "695": [
      "4.26"
    ], 
    "697": [
      "4.73", 
      "31.0"
    ], 
    "700": [
      "14.0"
    ], 
    "704": [
      "4.72", 
      "28.0"
    ], 
    "714": [
      "1320.0", 
      "134.707"
    ], 
    "717": [
      "134.81"
    ], 
    "720": [
      "1332.0", 
      "1325.4", 
      "1343.0"
    ], 
    "721": [
      "134.901", 
      "134.806"
    ], 
    "724": [
      "4.52", 
      "4.28"
    ], 
    "726": [
      "4.34"
    ], 
    "728": [
      "4.78", 
      "134.99901"
    ], 
    "731": [
      "250200.1"
    ], 
    "733": [
      "1312.0", 
      "4.41"
    ], 
    "734": [
      "1351.0"
    ], 
    "735": [
      "136.721"
    ], 
    "738": [
      "136.732", 
      "1326.0"
    ], 
    "739": [
      "4.77"
    ], 
    "740": [
      "136.731", 
      "4006.0"
    ], 
    "741": [
      "202.0"
    ], 
    "742": [
      "529.0", 
      "134.704"
    ], 
    "743": [
      "1323.0", 
      "522.0"
    ], 
    "745": [
      "4.51", 
      "134.705"
    ], 
    "746": [
      "1345.0", 
      "1341.0"
    ], 
    "748": [
      "136.726"
    ], 
    "749": [
      "136.735", 
      "4.37"
    ], 
    "750": [
      "136.729"
    ], 
    "751": [
      "25407.0"
    ], 
    "752": [
      "1334.0"
    ], 
    "753": [
      "136.722"
    ], 
    "757": [
      "136.724", 
      "1329.0"
    ], 
    "761": [
      "25403.0", 
      "4.55"
    ], 
    "763": [
      "1339.0"
    ], 
    "764": [
      "136.7321", 
      "136.725"
    ], 
    "765": [
      "526.0"
    ], 
    "771": [
      "136.723", 
      "134.703"
    ], 
    "776": [
      "281.0"
    ], 
    "778": [
      "1303.0"
    ], 
    "779": [
      "134.907", 
      "1325.0"
    ], 
    "780": [
      "1306.0"
    ], 
    "787": [
      "7.2"
    ], 
    "788": [
      "1328.0", 
      "136.756", 
      "280.0"
    ], 
    "796": [
      "1004.0"
    ], 
    "798": [
      "25408.0", 
      "25405.0", 
      "4.65"
    ], 
    "805": [
      "136.754"
    ], 
    "810": [
      "1325.2"
    ], 
    "813": [
      "50207.0"
    ], 
    "814": [
      "134.808"
    ], 
    "816": [
      "1311.0"
    ], 
    "817": [
      "4.58"
    ], 
    "822": [
      "136.73", 
      "7.3"
    ], 
    "823": [
      "136.747"
    ], 
    "834": [
      "136.779"
    ], 
    "835": [
      "512.0", 
      "1000.0"
    ], 
    "838": [
      "136.745", 
      "136.776", 
      "25.0"
    ], 
    "839": [
      "140.0"
    ], 
    "842": [
      "50205.0"
    ], 
    "846": [
      "25400.0"
    ], 
    "850": [
      "136.734"
    ], 
    "856": [
      "250200.117"
    ], 
    "863": [
      "204.0"
    ], 
    "864": [
      "136.791", 
      "50203.0", 
      "136.767"
    ], 
    "865": [
      "136.77"
    ], 
    "870": [
      "136.738"
    ], 
    "872": [
      "50204.0"
    ], 
    "874": [
      "134.709"
    ], 
    "876": [
      "134.908"
    ], 
    "880": [
      "50200.0"
    ], 
    "884": [
      "1102.0"
    ], 
    "890": [
      "25409.0"
    ], 
    "894": [
      "4.29"
    ], 
    "897": [
      "136.769"
    ], 
    "898": [
      "150.0"
    ], 
    "899": [
      "7.4"
    ], 
    "901": [
      "136.789"
    ], 
    "902": [
      "4.17"
    ], 
    "907": [
      "136.727"
    ], 
    "908": [
      "25402.0"
    ], 
    "912": [
      "136.736"
    ], 
    "913": [
      "136.744"
    ], 
    "916": [
      "136.748"
    ], 
    "917": [
      "136.771"
    ], 
    "920": [
      "136.743"
    ], 
    "926": [
      "136.774", 
      "136.757"
    ], 
    "927": [
      "136.746"
    ], 
    "936": [
      "50206.0"
    ], 
    "937": [
      "134.807"
    ], 
    "943": [
      "136.753"
    ], 
    "944": [
      "136.74"
    ], 
    "949": [
      "136.728"
    ], 
    "972": [
      "136.742"
    ], 
    "973": [
      "136.739", 
      "50208.0"
    ], 
    "974": [
      "10024.2"
    ], 
    "985": [
      "136.741"
    ], 
    "993": [
      "136.777"
    ], 
    "996": [
      "500202.0"
    ], 
    "999": [
      "136.775"
    ], 
    "1000": [
      "10003.0"
    ], 
    "1001": [
      "136.764"
    ], 
    "1011": [
      "500200.0"
    ], 
    "1013": [
      "1362.0"
    ], 
    "1015": [
      "20034.1"
    ], 
    "1016": [
      "10006.0"
    ], 
    "1018": [
      "1360.0"
    ], 
    "1023": [
      "1001.0"
    ], 
    "1025": [
      "500207.0"
    ], 
    "1029": [
      "136.749"
    ], 
    "1041": [
      "1363.0"
    ], 
    "1042": [
      "136.786"
    ], 
    "1044": [
      "25205.0", 
      "136.751", 
      "25202.0"
    ], 
    "1045": [
      "500203.0"
    ], 
    "1047": [
      "10024.6"
    ], 
    "1050": [
      "25214.0"
    ], 
    "1052": [
      "136.781"
    ], 
    "1059": [
      "10005.0", 
      "25203.0", 
      "25206.0"
    ], 
    "1061": [
      "136.765"
    ], 
    "1062": [
      "10009.0"
    ], 
    "1063": [
      "25209.0"
    ], 
    "1067": [
      "136.773", 
      "136.759"
    ], 
    "1069": [
      "10424.0"
    ], 
    "1070": [
      "10024.4"
    ], 
    "1071": [
      "10001.0"
    ], 
    "1075": [
      "136.763"
    ], 
    "1077": [
      "10004.0", 
      "13992501.0"
    ], 
    "1079": [
      "136.755"
    ], 
    "1080": [
      "136.768"
    ], 
    "1082": [
      "500204.0"
    ], 
    "1084": [
      "10042.0"
    ], 
    "1086": [
      "25207.0"
    ], 
    "1087": [
      "136.782"
    ], 
    "1089": [
      "25208.0"
    ], 
    "1090": [
      "20834.0"
    ], 
    "1091": [
      "136.75"
    ], 
    "1092": [
      "500206.0", 
      "136.752"
    ], 
    "1093": [
      "10002.0"
    ], 
    "1095": [
      "1356.0"
    ], 
    "1096": [
      "10008.0"
    ], 
    "1101": [
      "136.766"
    ], 
    "1103": [
      "136.785"
    ], 
    "1106": [
      "13992502.0"
    ], 
    "1111": [
      "10071.0"
    ], 
    "1113": [
      "136.772"
    ], 
    "1117": [
      "136.78", 
      "10026.0"
    ], 
    "1118": [
      "136.784"
    ], 
    "1120": [
      "10007.0"
    ], 
    "1121": [
      "25204.0"
    ], 
    "1124": [
      "10024.0"
    ], 
    "1125": [
      "136.737"
    ], 
    "1126": [
      "136.761"
    ], 
    "1127": [
      "25200.0"
    ], 
    "1128": [
      "500205.0"
    ], 
    "1129": [
      "136.788"
    ], 
    "1135": [
      "20034.0"
    ], 
    "1139": [
      "515.0"
    ], 
    "1142": [
      "10025.0"
    ], 
    "1143": [
      "20034.2"
    ], 
    "1155": [
      "518.0"
    ], 
    "1165": [
      "136.758"
    ], 
    "1169": [
      "1361.0"
    ], 
    "1180": [
      "10023.0", 
      "250199.17"
    ], 
    "1182": [
      "136.787"
    ], 
    "1184": [
      "20434.0"
    ], 
    "1191": [
      "203.0"
    ], 
    "1201": [
      "10059.0", 
      "136.79"
    ], 
    "1214": [
      "10823.0"
    ], 
    "1220": [
      "136.762"
    ], 
    "1226": [
      "50202.0"
    ], 
    "1230": [
      "136.76"
    ], 
    "1232": [
      "10842.0"
    ], 
    "1235": [
      "11224.0"
    ], 
    "1254": [
      "12024.0"
    ], 
    "1267": [
      "20834.2"
    ], 
    "1272": [
      "136.783"
    ], 
    "1289": [
      "25210.0"
    ], 
    "1330": [
      "11623.0"
    ], 
    "1360": [
      "11642.0"
    ], 
    "1371": [
      "10825.0"
    ], 
    "1398": [
      "11625.0"
    ], 
    "1402": [
      "250207.0"
    ], 
    "1426": [
      "10824.0"
    ], 
    "1437": [
      "1361.17"
    ], 
    "1441": [
      "250205.0"
    ], 
    "1464": [
      "25211.0"
    ], 
    "1465": [
      "11624.0"
    ], 
    "1477": [
      "10826.0"
    ], 
    "1485": [
      "250200.0"
    ], 
    "1506": [
      "1362.17"
    ], 
    "1560": [
      "25212.0"
    ], 
    "1597": [
      "1363.17"
    ], 
    "1604": [
      "25213.0"
    ], 
    "1620": [
      "250204.0"
    ], 
    "1638": [
      "250206.0"
    ], 
    "1667": [
      "11626.0"
    ], 
    "1696": [
      "250203.0"
    ], 
    "1726": [
      "250202.0"
    ], 
    "2203": [
      "250207.17"
    ], 
    "2220": [
      "250205.17"
    ], 
    "2226": [
      "250206.17"
    ], 
    "2287": [
      "250204.17"
    ], 
    "2294": [
      "250200.17"
    ], 
    "2299": [
      "250202.17"
    ], 
    "2378": [
      "250208.17"
    ], 
    "2384": [
      "250203.17"
    ], 
    "2453": [
      "10225.0"
    ], 
    "2585": [
      "10224.0"
    ], 
    "2948": [
      "25211.17"
    ], 
    "3048": [
      "25213.17"
    ], 
    "3158": [
      "25212.17"
    ]
  }, 
  "workflows": {
    "1.0": [
      277
    ], 
    "10.0": [
      653
    ], 
    "1000.0": [
      834, 
      837
    ], 
    "10001.0": [
      1079, 
      1064
    ], 
    "10002.0": [
      1147, 
      1039
    ], 
    "10003.0": [
      996, 
      1005
    ], 
    "10004.0": [
      1123, 
      1031
    ], 
    "10005.0": [
      1032, 
      1086
    ], 
    "10006.0": [
      1048, 
      985
    ], 
    "10007.0": [
      1143, 
      1098
    ], 
    "10008.0": [
      1156, 
      1037
    ], 
    "10009.0": [
      1042, 
      1082
    ], 
    "1001.0": [
      1023
    ], 
    "1002.0": [
      449
    ], 
    "10023.0": [
      1260, 
      1101
    ], 
    "10024.0": [
      1109, 
      1140
    ], 
    "10024.1": [
      491
    ], 
    "10024.2": [
      993, 
      956
    ], 
    "10024.3": [
      463
    ], 
    "10024.4": [
      1084, 
      1056
    ], 
    "10024.5": [
      447
    ], 
    "10024.6": [
      1135, 
      960
    ], 
    "10025.0": [
      1199, 
      1086
    ], 
    "10026.0": [
      1153, 
      1081
    ], 
    "1003.0": [
      417
    ], 
    "1004.0": [
      796
    ], 
    "10042.0": [
      1119, 
      1049
    ], 
    "10059.0": [
      1248, 
      1154
    ], 
    "10071.0": [
      1121, 
      1101
    ], 
    "101.0": [
      128
    ], 
    "1010.0": [
      124
    ], 
    "102.0": [
      104
    ], 
    "1020.0": [
      48
    ], 
    "10224.0": [
      2504, 
      2667
    ], 
    "10225.0": [
      2492, 
      2414
    ], 
    "103.0": [
      267
    ], 
    "1030.0": [
      235
    ], 
    "10424.0": [
      1086, 
      1053
    ], 
    "105.0": [
      182
    ], 
    "106.0": [
      278
    ], 
    "107.0": [
      464
    ], 
    "108.0": [
      501
    ], 
    "10823.0": [
      1158, 
      1271
    ], 
    "10824.0": [
      1452, 
      1400
    ], 
    "10825.0": [
      1295, 
      1448
    ], 
    "10826.0": [
      1537, 
      1417
    ], 
    "10842.0": [
      1244, 
      1221
    ], 
    "109.0": [
      619, 
      585
    ], 
    "11.0": [
      627, 
      703
    ], 
    "110.0": [
      306
    ], 
    "1102.0": [
      884
    ], 
    "111.0": [
      372
    ], 
    "112.0": [
      431
    ], 
    "11224.0": [
      1215, 
      1255
    ], 
    "113.0": [
      426
    ], 
    "114.0": [
      464
    ], 
    "115.0": [
      441
    ], 
    "116.0": [
      465
    ], 
    "11623.0": [
      1300, 
      1361
    ], 
    "11624.0": [
      1510, 
      1421
    ], 
    "11625.0": [
      1410, 
      1387
    ], 
    "11626.0": [
      1552, 
      1782
    ], 
    "11642.0": [
      1327, 
      1393
    ], 
    "117.0": [
      458
    ], 
    "118.0": [
      677, 
      507
    ], 
    "119.0": [
      387
    ], 
    "12.0": [
      483
    ], 
    "120.0": [
      312
    ], 
    "12024.0": [
      1271, 
      1237
    ], 
    "121.0": [
      435
    ], 
    "122.0": [
      323
    ], 
    "123.1": [
      159
    ], 
    "123.2": [
      159
    ], 
    "123.3": [
      158
    ], 
    "124.1": [
      160
    ], 
    "124.2": [
      150
    ], 
    "124.4": [
      154
    ], 
    "124.5": [
      154
    ], 
    "124.6": [
      149
    ], 
    "125.0": [
      384
    ], 
    "126.0": [
      325
    ], 
    "127.0": [
      316
    ], 
    "128.0": [
      308
    ], 
    "129.0": [
      306
    ], 
    "13.0": [
      400
    ], 
    "130.0": [
      363
    ], 
    "1301.0": [
      385
    ], 
    "1302.0": [
      473
    ], 
    "1303.0": [
      820, 
      737
    ], 
    "1306.0": [
      861, 
      699
    ], 
    "1307.0": [
      273
    ], 
    "1308.0": [
      260
    ], 
    "1309.0": [
      595, 
      638
    ], 
    "131.0": [
      375
    ], 
    "1310.0": [
      681, 
      591
    ], 
    "1311.0": [
      896, 
      737
    ], 
    "1312.0": [
      691, 
      775
    ], 
    "1313.0": [
      707, 
      611
    ], 
    "1314.0": [
      619, 
      707
    ], 
    "1315.0": [
      661, 
      540
    ], 
    "1316.0": [
      721, 
      631
    ], 
    "1317.0": [
      635, 
      624
    ], 
    "1318.0": [
      720, 
      597
    ], 
    "1319.0": [
      629, 
      672
    ], 
    "132.0": [
      453
    ], 
    "1320.0": [
      700, 
      728
    ], 
    "1321.0": [
      602, 
      498
    ], 
    "1322.0": [
      676, 
      673
    ], 
    "1323.0": [
      727, 
      760
    ], 
    "1324.0": [
      751, 
      637
    ], 
    "1325.0": [
      802, 
      756
    ], 
    "1325.1": [
      292
    ], 
    "1325.2": [
      719, 
      901
    ], 
    "1325.3": [
      263
    ], 
    "1325.4": [
      631, 
      810
    ], 
    "1325.5": [
      253
    ], 
    "1326.0": [
      732, 
      745
    ], 
    "1327.0": [
      696, 
      571
    ], 
    "1328.0": [
      770, 
      806
    ], 
    "1329.0": [
      802, 
      713
    ], 
    "133.0": [
      509
    ], 
    "1330.0": [
      710, 
      497
    ], 
    "1331.0": [
      703, 
      676
    ], 
    "1332.0": [
      643, 
      797
    ], 
    "1333.0": [
      755, 
      621
    ], 
    "1334.0": [
      673, 
      832
    ], 
    "1335.0": [
      677, 
      643
    ], 
    "1336.0": [
      722, 
      595
    ], 
    "1337.0": [
      734, 
      641
    ], 
    "1338.0": [
      692, 
      685
    ], 
    "1339.0": [
      846, 
      681
    ], 
    "134.0": [
      465
    ], 
    "134.701": [
      651
    ], 
    "134.702": [
      591
    ], 
    "134.703": [
      771
    ], 
    "134.704": [
      742
    ], 
    "134.705": [
      745
    ], 
    "134.706": [
      600
    ], 
    "134.707": [
      714
    ], 
    "134.708": [
      597
    ], 
    "134.709": [
      874
    ], 
    "134.71": [
      611
    ], 
    "134.801": [
      660
    ], 
    "134.802": [
      616
    ], 
    "134.803": [
      683
    ], 
    "134.804": [
      649
    ], 
    "134.805": [
      577
    ], 
    "134.806": [
      721
    ], 
    "134.807": [
      937
    ], 
    "134.808": [
      814
    ], 
    "134.809": [
      639
    ], 
    "134.81": [
      717
    ], 
    "134.811": [
      606
    ], 
    "134.812": [
      636
    ], 
    "134.813": [
      234
    ], 
    "134.901": [
      721
    ], 
    "134.902": [
      627
    ], 
    "134.903": [
      688, 
      701
    ], 
    "134.904": [
      631
    ], 
    "134.905": [
      685
    ], 
    "134.906": [
      643
    ], 
    "134.907": [
      779
    ], 
    "134.908": [
      876
    ], 
    "134.909": [
      682, 
      639
    ], 
    "134.91": [
      680
    ], 
    "134.911": [
      595
    ], 
    "134.912": [
      665
    ], 
    "134.99601": [
      634
    ], 
    "134.99602": [
      568
    ], 
    "134.99603": [
      659
    ], 
    "134.99901": [
      728
    ], 
    "1340.0": [
      647, 
      649
    ], 
    "1341.0": [
      714, 
      778
    ], 
    "1343.0": [
      857, 
      584
    ], 
    "1344.0": [
      751, 
      544
    ], 
    "1345.0": [
      747, 
      745
    ], 
    "1347.0": [
      685, 
      621
    ], 
    "1348.0": [
      651, 
      654
    ], 
    "1349.0": [
      574, 
      553
    ], 
    "135.1": [
      358
    ], 
    "135.11": [
      351
    ], 
    "135.12": [
      404
    ], 
    "135.13": [
      232
    ], 
    "135.2": [
      317
    ], 
    "135.3": [
      330
    ], 
    "135.4": [
      337
    ], 
    "135.5": [
      379
    ], 
    "135.6": [
      355
    ], 
    "135.7": [
      399
    ], 
    "135.8": [
      59
    ], 
    "135.9": [
      363
    ], 
    "1350.0": [
      676, 
      496
    ], 
    "1351.0": [
      759, 
      709
    ], 
    "1352.0": [
      715, 
      553
    ], 
    "1353.0": [
      620, 
      604
    ], 
    "1354.0": [
      643, 
      604
    ], 
    "1355.0": [
      618, 
      555
    ], 
    "1356.0": [
      1095
    ], 
    "136.721": [
      735
    ], 
    "136.722": [
      753
    ], 
    "136.723": [
      771
    ], 
    "136.724": [
      847, 
      667
    ], 
    "136.725": [
      764
    ], 
    "136.726": [
      800, 
      696
    ], 
    "136.727": [
      907
    ], 
    "136.728": [
      949
    ], 
    "136.729": [
      788, 
      712
    ], 
    "136.73": [
      822
    ], 
    "136.731": [
      740
    ], 
    "136.732": [
      738
    ], 
    "136.7321": [
      801, 
      727
    ], 
    "136.733": [
      227
    ], 
    "136.734": [
      850
    ], 
    "136.735": [
      749
    ], 
    "136.736": [
      912
    ], 
    "136.737": [
      1125
    ], 
    "136.738": [
      937, 
      803
    ], 
    "136.739": [
      1014, 
      932
    ], 
    "136.74": [
      944
    ], 
    "136.741": [
      985
    ], 
    "136.742": [
      972
    ], 
    "136.743": [
      920
    ], 
    "136.744": [
      913
    ], 
    "136.745": [
      838
    ], 
    "136.746": [
      927
    ], 
    "136.747": [
      823
    ], 
    "136.748": [
      916
    ], 
    "136.749": [
      1029
    ], 
    "136.75": [
      1091
    ], 
    "136.751": [
      1044
    ], 
    "136.752": [
      1092
    ], 
    "136.753": [
      943
    ], 
    "136.754": [
      865, 
      746
    ], 
    "136.755": [
      1079
    ], 
    "136.756": [
      837, 
      740
    ], 
    "136.757": [
      926
    ], 
    "136.758": [
      1165
    ], 
    "136.759": [
      1067
    ], 
    "136.76": [
      1230
    ], 
    "136.761": [
      1126
    ], 
    "136.7611": [
      225
    ], 
    "136.762": [
      1220
    ], 
    "136.763": [
      1075
    ], 
    "136.764": [
      1001
    ], 
    "136.765": [
      1061
    ], 
    "136.766": [
      1101
    ], 
    "136.767": [
      921, 
      808
    ], 
    "136.768": [
      1080
    ], 
    "136.769": [
      897
    ], 
    "136.77": [
      865
    ], 
    "136.771": [
      917
    ], 
    "136.772": [
      1113
    ], 
    "136.773": [
      1067
    ], 
    "136.774": [
      926
    ], 
    "136.775": [
      999
    ], 
    "136.776": [
      838
    ], 
    "136.777": [
      993
    ], 
    "136.778": [
      736, 
      598
    ], 
    "136.779": [
      912, 
      756
    ], 
    "136.78": [
      1117
    ], 
    "136.781": [
      1052
    ], 
    "136.782": [
      1087
    ], 
    "136.783": [
      1272
    ], 
    "136.784": [
      1118
    ], 
    "136.785": [
      1103
    ], 
    "136.786": [
      1042
    ], 
    "136.787": [
      1182
    ], 
    "136.788": [
      1129
    ], 
    "136.789": [
      886, 
      916
    ], 
    "136.79": [
      1201
    ], 
    "136.791": [
      886, 
      843
    ], 
    "1360.0": [
      981, 
      1055
    ], 
    "1361.0": [
      1169
    ], 
    "1361.17": [
      1462, 
      1413
    ], 
    "1362.0": [
      1009, 
      1018
    ], 
    "1362.17": [
      1555, 
      1457
    ], 
    "1363.0": [
      1041
    ], 
    "1363.17": [
      1632, 
      1563
    ], 
    "1364.0": [
      593, 
      607
    ], 
    "1365.0": [
      651, 
      603
    ], 
    "1366.0": [
      664, 
      530
    ], 
    "139901.0": [
      588, 
      657
    ], 
    "139902.0": [
      750, 
      554
    ], 
    "13992501.0": [
      1028, 
      1127
    ], 
    "13992502.0": [
      981, 
      1231
    ], 
    "14.0": [
      700
    ], 
    "140.0": [
      887, 
      791
    ], 
    "140.51": [
      261, 
      312
    ], 
    "140.52": [
      182, 
      161
    ], 
    "140.53": [
      312
    ], 
    "140.54": [
      298
    ], 
    "144.6": [
      352, 
      330
    ], 
    "145.0": [
      11, 
      17
    ], 
    "15.0": [
      401
    ], 
    "150.0": [
      898
    ], 
    "150.1": [
      323
    ], 
    "150.2": [
      309
    ], 
    "150.3": [
      301
    ], 
    "16.0": [
      456
    ], 
    "17.0": [
      391
    ], 
    "18.0": [
      392
    ], 
    "19.0": [
      428
    ], 
    "2.0": [
      328
    ], 
    "20.0": [
      444
    ], 
    "200.0": [
      599
    ], 
    "20034.0": [
      1135
    ], 
    "20034.1": [
      1015
    ], 
    "20034.2": [
      1143
    ], 
    "202.0": [
      741
    ], 
    "203.0": [
      1191
    ], 
    "204.0": [
      863
    ], 
    "20434.0": [
      1184
    ], 
    "205.0": [
      632
    ], 
    "20834.0": [
      1090
    ], 
    "20834.2": [
      1267
    ], 
    "21.0": [
      437
    ], 
    "22.0": [
      511
    ], 
    "23.0": [
      581, 
      629
    ], 
    "24.0": [
      623
    ], 
    "25.0": [
      903, 
      774
    ], 
    "250199.0": [
      590, 
      534
    ], 
    "250199.17": [
      1117, 
      1244
    ], 
    "250200.0": [
      1485
    ], 
    "250200.1": [
      871, 
      591
    ], 
    "250200.117": [
      955, 
      757
    ], 
    "250200.17": [
      2317, 
      2272
    ], 
    "250202.0": [
      1726
    ], 
    "250202.17": [
      2324, 
      2274
    ], 
    "250203.0": [
      1696
    ], 
    "250203.17": [
      2492, 
      2277
    ], 
    "250204.0": [
      1620
    ], 
    "250204.17": [
      2360, 
      2214
    ], 
    "250205.0": [
      1441
    ], 
    "250205.17": [
      2281, 
      2160
    ], 
    "250206.0": [
      1638
    ], 
    "250206.17": [
      2296, 
      2156
    ], 
    "250207.0": [
      1402
    ], 
    "250207.17": [
      2277, 
      2129
    ], 
    "250208.17": [
      2442, 
      2314
    ], 
    "250399.0": [
      227, 
      188
    ], 
    "250400.0": [
      408
    ], 
    "250402.0": [
      447
    ], 
    "250403.0": [
      393
    ], 
    "250405.0": [
      443
    ], 
    "250406.0": [
      403
    ], 
    "250407.0": [
      398
    ], 
    "250408.0": [
      426
    ], 
    "250409.0": [
      446
    ], 
    "25200.0": [
      1127
    ], 
    "25202.0": [
      1044
    ], 
    "25203.0": [
      1059
    ], 
    "25204.0": [
      1121
    ], 
    "25205.0": [
      1044
    ], 
    "25206.0": [
      994, 
      1124
    ], 
    "25207.0": [
      1086
    ], 
    "25208.0": [
      1024, 
      1155
    ], 
    "25209.0": [
      1063
    ], 
    "25210.0": [
      1289
    ], 
    "25211.0": [
      1464
    ], 
    "25211.17": [
      3083, 
      2814
    ], 
    "25212.0": [
      1560
    ], 
    "25212.17": [
      3374, 
      2942
    ], 
    "25213.0": [
      1604
    ], 
    "25213.17": [
      3120, 
      2976
    ], 
    "25214.0": [
      1003, 
      1098
    ], 
    "25400.0": [
      946, 
      746
    ], 
    "25402.0": [
      908
    ], 
    "25403.0": [
      796, 
      727
    ], 
    "25405.0": [
      865, 
      731
    ], 
    "25406.0": [
      468
    ], 
    "25407.0": [
      782, 
      721
    ], 
    "25408.0": [
      798
    ], 
    "25409.0": [
      890
    ], 
    "26.0": [
      530
    ], 
    "27.0": [
      520
    ], 
    "28.0": [
      704
    ], 
    "280.0": [
      788
    ], 
    "281.0": [
      795, 
      757
    ], 
    "29.0": [
      713, 
      523
    ], 
    "3.0": [
      499
    ], 
    "30.0": [
      570
    ], 
    "300.0": [
      548, 
      588
    ], 
    "301.0": [
      679
    ], 
    "302.0": [
      520
    ], 
    "31.0": [
      697
    ], 
    "32.0": [
      546
    ], 
    "33.0": [
      626
    ], 
    "34.0": [
      571
    ], 
    "35.0": [
      644
    ], 
    "36.0": [
      677
    ], 
    "37.0": [
      649
    ], 
    "38.0": [
      607
    ], 
    "39.0": [
      609
    ], 
    "4.17": [
      974, 
      831
    ], 
    "4.22": [
      370
    ], 
    "4.23": [
      716, 
      545
    ], 
    "4.24": [
      576
    ], 
    "4.25": [
      585
    ], 
    "4.26": [
      695
    ], 
    "4.27": [
      669
    ], 
    "4.28": [
      701, 
      747
    ], 
    "4.29": [
      1000, 
      789
    ], 
    "4.34": [
      726
    ], 
    "4.36": [
      657
    ], 
    "4.37": [
      749
    ], 
    "4.4": [
      639
    ], 
    "4.41": [
      733
    ], 
    "4.42": [
      596
    ], 
    "4.43": [
      595, 
      581
    ], 
    "4.44": [
      653
    ], 
    "4.45": [
      669
    ], 
    "4.51": [
      745
    ], 
    "4.52": [
      724
    ], 
    "4.53": [
      672
    ], 
    "4.54": [
      614
    ], 
    "4.55": [
      761
    ], 
    "4.57": [
      681
    ], 
    "4.58": [
      817
    ], 
    "4.6": [
      468
    ], 
    "4.61": [
      612
    ], 
    "4.62": [
      595
    ], 
    "4.63": [
      644
    ], 
    "4.64": [
      588
    ], 
    "4.65": [
      798
    ], 
    "4.67": [
      636
    ], 
    "4.68": [
      631
    ], 
    "4.71": [
      618
    ], 
    "4.72": [
      704
    ], 
    "4.73": [
      697
    ], 
    "4.74": [
      617
    ], 
    "4.75": [
      635
    ], 
    "4.76": [
      641
    ], 
    "4.77": [
      739
    ], 
    "4.78": [
      728
    ], 
    "4000.0": [
      493, 
      472
    ], 
    "4001.0": [
      355, 
      388
    ], 
    "4002.0": [
      333, 
      345
    ], 
    "4003.0": [
      334, 
      369
    ], 
    "4006.0": [
      720, 
      760
    ], 
    "4007.0": [
      429
    ], 
    "4008.0": [
      266
    ], 
    "43.0": [
      569
    ], 
    "44.0": [
      629
    ], 
    "45.0": [
      596
    ], 
    "5.1": [
      224
    ], 
    "5.2": [
      201
    ], 
    "5.3": [
      206
    ], 
    "5.4": [
      215
    ], 
    "5.5": [
      233
    ], 
    "5.6": [
      234
    ], 
    "5.7": [
      233
    ], 
    "500199.0": [
      250, 
      248
    ], 
    "500200.0": [
      1011
    ], 
    "500200.1": [
      597, 
      555
    ], 
    "500202.0": [
      996
    ], 
    "500203.0": [
      1045
    ], 
    "500204.0": [
      1082
    ], 
    "500205.0": [
      1128
    ], 
    "500206.0": [
      1092
    ], 
    "500207.0": [
      1025
    ], 
    "50200.0": [
      907, 
      853
    ], 
    "50202.0": [
      1226
    ], 
    "50203.0": [
      861, 
      867
    ], 
    "50204.0": [
      907, 
      837
    ], 
    "50205.0": [
      842
    ], 
    "50206.0": [
      983, 
      889
    ], 
    "50207.0": [
      813
    ], 
    "50208.0": [
      973
    ], 
    "503.0": [
      84
    ], 
    "504.0": [
      76
    ], 
    "505.0": [
      80
    ], 
    "506.0": [
      81
    ], 
    "507.0": [
      82
    ], 
    "508.0": [
      79
    ], 
    "509.0": [
      90
    ], 
    "510.0": [
      86
    ], 
    "512.0": [
      835
    ], 
    "513.0": [
      197, 
      181
    ], 
    "514.0": [
      292
    ], 
    "515.0": [
      1171, 
      1107
    ], 
    "516.0": [
      147, 
      143
    ], 
    "517.0": [
      565, 
      581
    ], 
    "518.0": [
      1185, 
      1126
    ], 
    "519.0": [
      162, 
      146
    ], 
    "520.0": [
      637, 
      740
    ], 
    "521.0": [
      174, 
      152
    ], 
    "522.0": [
      743
    ], 
    "523.0": [
      174
    ], 
    "524.0": [
      609, 
      510
    ], 
    "525.0": [
      150, 
      154
    ], 
    "526.0": [
      765
    ], 
    "527.0": [
      608, 
      564
    ], 
    "528.0": [
      136, 
      142
    ], 
    "529.0": [
      742
    ], 
    "530.0": [
      578
    ], 
    "531.0": [
      76
    ], 
    "534.0": [
      137
    ], 
    "535.0": [
      344
    ], 
    "541.0": [
      82
    ], 
    "545.0": [
      80
    ], 
    "551.0": [
      170
    ], 
    "552.0": [
      482
    ], 
    "554.0": [
      733, 
      622
    ], 
    "555.0": [
      205
    ], 
    "556.0": [
      359
    ], 
    "560.0": [
      80
    ], 
    "561.0": [
      81
    ], 
    "562.0": [
      190
    ], 
    "6.0": [
      415
    ], 
    "7.0": [
      334
    ], 
    "7.1": [
      356
    ], 
    "7.2": [
      787
    ], 
    "7.3": [
      822
    ], 
    "7.4": [
      899
    ], 
    "8.0": [
      282
    ], 
    "9.0": [
      581
    ]
  }
}
